telecom_coworker/__init__.py
telecom_coworker/coworker.py
telecom_coworker/dispatcher.py
telecom_coworker/kazoo_helper.py
telecom_coworker/log.py
telecom_coworker/models.py
telecom_coworker/recorder.py
telecom_coworker/utils.py
telecom_coworker/version.py
telecom_coworker/cache/__init__.py
telecom_coworker/cache/big_cache.py
telecom_coworker/cache/children_data_cache.py
telecom_coworker/cache/tasks_cache.py
telecom_coworker/cache/workers_cache.py
telecom_coworker/web/__init__.py
telecom_coworker/web/api.py
telecom_coworker/web/commands.py
telecom_coworker/web/config.py
telecom_coworker/web/db.py
telecom_coworker/web/pages.py
telecom_coworker/web/stats.py
telecom_coworker/web/utils.py
telecom_coworker/web/zk.py
telecom_coworker/web/static/tyy.png
telecom_coworker/web/static/css/bulma.css
telecom_coworker/web/static/js/fontawesome.js
telecom_coworker/web/static/js/vue.js
telecom_coworker/web/templates/index.html
telecom_coworker/web/templates/layout.html
telecom_coworker/web/templates/record.html
telecom_coworker/web/templates/task.html
telecom_coworker/web/templates/workers.html
test/__init__.py
test/main.py
tele_coworker-0.0.11.dist-info/METADATA
tele_coworker-0.0.11.dist-info/WHEEL
tele_coworker-0.0.11.dist-info/entry_points.txt
tele_coworker-0.0.11.dist-info/top_level.txt
tele_coworker-0.0.11.dist-info/RECORD
