Metadata-Version: 2.1
Name: tele-coworker
Version: 0.0.11
Summary: test it
Home-page: https://www.ctyun.cn/h5/home/
Author: Zhennan Hu
Author-email: huzn@chinatelecom.cn
License: GNU General Public License v3.0
Platform: UNKNOWN
Requires-Dist: click (==7.1.2)
Requires-Dist: Flask (==1.1.2)
Requires-Dist: Flask-SQLAlchemy (==2.4.4)
Requires-Dist: itsdangerous (==1.1.0)
Requires-Dist: Jinja2 (==2.11.2)
Requires-Dist: kazoo (==2.8.0)
Requires-Dist: MarkupSafe (==1.1.1)
Requires-Dist: numpy (==1.19.2)
Requires-Dist: PyMySQL (==0.10.1)
Requires-Dist: six (==1.15.0)
Requires-Dist: SQLAlchemy (==1.3.20)
Requires-Dist: Werkzeug (==1.0.1)
Requires-Dist: PyYAML (==5.3.1)
Requires-Dist: pytz (==2020.4)
